{
  "metadata": {
    "id": "tier2_omaha4_5p",
    "config": {
      "gameVariant": "omaha4",
      "playerCount": 5,
      "iterations": 100000
    },
    "createdAt": "2026-02-10T04:57:33.537Z",
    "durationMs": 30713
  },
  "statistics": {
    "handTypeDistribution": [
      {
        "handType": 0,
        "name": "High Card",
        "count": 2935,
        "percentage": 2.94,
        "wins": 0,
        "winRate": 0
      },
      {
        "handType": 1,
        "name": "One Pair",
        "count": 26437,
        "percentage": 26.44,
        "wins": 128,
        "winRate": 0.48
      },
      {
        "handType": 2,
        "name": "Two Pair",
        "count": 36760,
        "percentage": 36.76,
        "wins": 3090,
        "winRate": 8.41
      },
      {
        "handType": 3,
        "name": "Three of a Kind",
        "count": 8680,
        "percentage": 8.68,
        "wins": 2391,
        "winRate": 27.55
      },
      {
        "handType": 4,
        "name": "Straight",
        "count": 11382,
        "percentage": 11.38,
        "wins": 6032,
        "winRate": 53
      },
      {
        "handType": 5,
        "name": "Flush",
        "count": 6865,
        "percentage": 6.87,
        "wins": 3965,
        "winRate": 57.76
      },
      {
        "handType": 6,
        "name": "Full House",
        "count": 6372,
        "percentage": 6.37,
        "wins": 4948,
        "winRate": 77.65
      },
      {
        "handType": 7,
        "name": "Four of a Kind",
        "count": 484,
        "percentage": 0.48,
        "wins": 480,
        "winRate": 99.17
      },
      {
        "handType": 8,
        "name": "Straight Flush",
        "count": 85,
        "percentage": 0.08,
        "wins": 83,
        "winRate": 97.65
      }
    ],
    "overallWinRate": 21.12,
    "probabilityMatrix": [
      [
        {
          "heroHand": "High Card",
          "oppHand": "High Card",
          "threatPct": 18.74,
          "count": 0,
          "wins": 0,
          "winRate": 0
        },
        {
          "heroHand": "High Card",
          "oppHand": "One Pair",
          "threatPct": 83.58,
          "count": 60,
          "wins": 0,
          "winRate": 0
        },
        {
          "heroHand": "High Card",
          "oppHand": "Two Pair",
          "threatPct": 75.5,
          "count": 763,
          "wins": 0,
          "winRate": 0
        },
        {
          "heroHand": "High Card",
          "oppHand": "Three of a Kind",
          "threatPct": 30.53,
          "count": 438,
          "wins": 0,
          "winRate": 0
        },
        {
          "heroHand": "High Card",
          "oppHand": "Straight",
          "threatPct": 42.45,
          "count": 1052,
          "wins": 0,
          "winRate": 0
        },
        {
          "heroHand": "High Card",
          "oppHand": "Flush",
          "threatPct": 21.02,
          "count": 609,
          "wins": 0,
          "winRate": 0
        },
        {
          "heroHand": "High Card",
          "oppHand": "Full House",
          "threatPct": 0,
          "count": 0,
          "wins": 0,
          "winRate": 0
        },
        {
          "heroHand": "High Card",
          "oppHand": "Four of a Kind",
          "threatPct": 0,
          "count": 0,
          "wins": 0,
          "winRate": 0
        },
        {
          "heroHand": "High Card",
          "oppHand": "Straight Flush",
          "threatPct": 0.44,
          "count": 13,
          "wins": 0,
          "winRate": 0
        }
      ],
      [
        {
          "heroHand": "One Pair",
          "oppHand": "High Card",
          "threatPct": 15.03,
          "count": 0,
          "wins": 0,
          "winRate": 0
        },
        {
          "heroHand": "One Pair",
          "oppHand": "One Pair",
          "threatPct": 75.1,
          "count": 543,
          "wins": 128,
          "winRate": 23.6
        },
        {
          "heroHand": "One Pair",
          "oppHand": "Two Pair",
          "threatPct": 78.64,
          "count": 5898,
          "wins": 0,
          "winRate": 0
        },
        {
          "heroHand": "One Pair",
          "oppHand": "Three of a Kind",
          "threatPct": 29,
          "count": 3750,
          "wins": 0,
          "winRate": 0
        },
        {
          "heroHand": "One Pair",
          "oppHand": "Straight",
          "threatPct": 38.07,
          "count": 7779,
          "wins": 0,
          "winRate": 0
        },
        {
          "heroHand": "One Pair",
          "oppHand": "Flush",
          "threatPct": 20.28,
          "count": 4791,
          "wins": 0,
          "winRate": 0
        },
        {
          "heroHand": "One Pair",
          "oppHand": "Full House",
          "threatPct": 12.83,
          "count": 3336,
          "wins": 0,
          "winRate": 0
        },
        {
          "heroHand": "One Pair",
          "oppHand": "Four of a Kind",
          "threatPct": 0.89,
          "count": 234,
          "wins": 0,
          "winRate": 0
        },
        {
          "heroHand": "One Pair",
          "oppHand": "Straight Flush",
          "threatPct": 0.4,
          "count": 106,
          "wins": 0,
          "winRate": 0
        }
      ],
      [
        {
          "heroHand": "Two Pair",
          "oppHand": "High Card",
          "threatPct": 8.34,
          "count": 0,
          "wins": 0,
          "winRate": 0
        },
        {
          "heroHand": "Two Pair",
          "oppHand": "One Pair",
          "threatPct": 62.06,
          "count": 570,
          "wins": 570,
          "winRate": 100
        },
        {
          "heroHand": "Two Pair",
          "oppHand": "Two Pair",
          "threatPct": 85.16,
          "count": 7322,
          "wins": 2520,
          "winRate": 34.4
        },
        {
          "heroHand": "Two Pair",
          "oppHand": "Three of a Kind",
          "threatPct": 28.19,
          "count": 4977,
          "wins": 0,
          "winRate": 0
        },
        {
          "heroHand": "Two Pair",
          "oppHand": "Straight",
          "threatPct": 30.12,
          "count": 7409,
          "wins": 0,
          "winRate": 0
        },
        {
          "heroHand": "Two Pair",
          "oppHand": "Flush",
          "threatPct": 19.71,
          "count": 5459,
          "wins": 0,
          "winRate": 0
        },
        {
          "heroHand": "Two Pair",
          "oppHand": "Full House",
          "threatPct": 28.28,
          "count": 10280,
          "wins": 0,
          "winRate": 0
        },
        {
          "heroHand": "Two Pair",
          "oppHand": "Four of a Kind",
          "threatPct": 1.76,
          "count": 646,
          "wins": 0,
          "winRate": 0
        },
        {
          "heroHand": "Two Pair",
          "oppHand": "Straight Flush",
          "threatPct": 0.26,
          "count": 97,
          "wins": 0,
          "winRate": 0
        }
      ],
      [
        {
          "heroHand": "Three of a Kind",
          "oppHand": "High Card",
          "threatPct": 11.05,
          "count": 0,
          "wins": 0,
          "winRate": 0
        },
        {
          "heroHand": "Three of a Kind",
          "oppHand": "One Pair",
          "threatPct": 60.08,
          "count": 188,
          "wins": 188,
          "winRate": 100
        },
        {
          "heroHand": "Three of a Kind",
          "oppHand": "Two Pair",
          "threatPct": 68.36,
          "count": 1727,
          "wins": 1727,
          "winRate": 100
        },
        {
          "heroHand": "Three of a Kind",
          "oppHand": "Three of a Kind",
          "threatPct": 35.02,
          "count": 1050,
          "wins": 476,
          "winRate": 45.3
        },
        {
          "heroHand": "Three of a Kind",
          "oppHand": "Straight",
          "threatPct": 29.01,
          "count": 1830,
          "wins": 0,
          "winRate": 0
        },
        {
          "heroHand": "Three of a Kind",
          "oppHand": "Flush",
          "threatPct": 18.05,
          "count": 1275,
          "wins": 0,
          "winRate": 0
        },
        {
          "heroHand": "Three of a Kind",
          "oppHand": "Full House",
          "threatPct": 27.82,
          "count": 2073,
          "wins": 0,
          "winRate": 0
        },
        {
          "heroHand": "Three of a Kind",
          "oppHand": "Four of a Kind",
          "threatPct": 5.92,
          "count": 514,
          "wins": 0,
          "winRate": 0
        },
        {
          "heroHand": "Three of a Kind",
          "oppHand": "Straight Flush",
          "threatPct": 0.26,
          "count": 23,
          "wins": 0,
          "winRate": 0
        }
      ],
      [
        {
          "heroHand": "Straight",
          "oppHand": "High Card",
          "threatPct": 15.13,
          "count": 0,
          "wins": 0,
          "winRate": 0
        },
        {
          "heroHand": "Straight",
          "oppHand": "One Pair",
          "threatPct": 70.81,
          "count": 185,
          "wins": 185,
          "winRate": 100
        },
        {
          "heroHand": "Straight",
          "oppHand": "Two Pair",
          "threatPct": 75.34,
          "count": 1942,
          "wins": 1942,
          "winRate": 100
        },
        {
          "heroHand": "Straight",
          "oppHand": "Three of a Kind",
          "threatPct": 25.99,
          "count": 1177,
          "wins": 1177,
          "winRate": 100
        },
        {
          "heroHand": "Straight",
          "oppHand": "Straight",
          "threatPct": 52,
          "count": 4369,
          "wins": 2728,
          "winRate": 62.4
        },
        {
          "heroHand": "Straight",
          "oppHand": "Flush",
          "threatPct": 21.17,
          "count": 2179,
          "wins": 0,
          "winRate": 0
        },
        {
          "heroHand": "Straight",
          "oppHand": "Full House",
          "threatPct": 12.47,
          "count": 1388,
          "wins": 0,
          "winRate": 0
        },
        {
          "heroHand": "Straight",
          "oppHand": "Four of a Kind",
          "threatPct": 0.77,
          "count": 88,
          "wins": 0,
          "winRate": 0
        },
        {
          "heroHand": "Straight",
          "oppHand": "Straight Flush",
          "threatPct": 0.47,
          "count": 54,
          "wins": 0,
          "winRate": 0
        }
      ],
      [
        {
          "heroHand": "Flush",
          "oppHand": "High Card",
          "threatPct": 10.49,
          "count": 0,
          "wins": 0,
          "winRate": 0
        },
        {
          "heroHand": "Flush",
          "oppHand": "One Pair",
          "threatPct": 64.49,
          "count": 75,
          "wins": 75,
          "winRate": 100
        },
        {
          "heroHand": "Flush",
          "oppHand": "Two Pair",
          "threatPct": 78.27,
          "count": 839,
          "wins": 839,
          "winRate": 100
        },
        {
          "heroHand": "Flush",
          "oppHand": "Three of a Kind",
          "threatPct": 27.17,
          "count": 605,
          "wins": 605,
          "winRate": 100
        },
        {
          "heroHand": "Flush",
          "oppHand": "Straight",
          "threatPct": 34.89,
          "count": 1207,
          "wins": 1207,
          "winRate": 100
        },
        {
          "heroHand": "Flush",
          "oppHand": "Flush",
          "threatPct": 47.98,
          "count": 2703,
          "wins": 1239,
          "winRate": 45.8
        },
        {
          "heroHand": "Flush",
          "oppHand": "Full House",
          "threatPct": 19.16,
          "count": 1279,
          "wins": 0,
          "winRate": 0
        },
        {
          "heroHand": "Flush",
          "oppHand": "Four of a Kind",
          "threatPct": 1.57,
          "count": 107,
          "wins": 0,
          "winRate": 0
        },
        {
          "heroHand": "Flush",
          "oppHand": "Straight Flush",
          "threatPct": 0.73,
          "count": 50,
          "wins": 0,
          "winRate": 0
        }
      ],
      [
        {
          "heroHand": "Full House",
          "oppHand": "High Card",
          "threatPct": 0,
          "count": 0,
          "wins": 0,
          "winRate": 0
        },
        {
          "heroHand": "Full House",
          "oppHand": "One Pair",
          "threatPct": 47.25,
          "count": 7,
          "wins": 7,
          "winRate": 100
        },
        {
          "heroHand": "Full House",
          "oppHand": "Two Pair",
          "threatPct": 84.31,
          "count": 1365,
          "wins": 1365,
          "winRate": 100
        },
        {
          "heroHand": "Full House",
          "oppHand": "Three of a Kind",
          "threatPct": 32.88,
          "count": 820,
          "wins": 820,
          "winRate": 100
        },
        {
          "heroHand": "Full House",
          "oppHand": "Straight",
          "threatPct": 22.46,
          "count": 832,
          "wins": 832,
          "winRate": 100
        },
        {
          "heroHand": "Full House",
          "oppHand": "Flush",
          "threatPct": 18.36,
          "count": 799,
          "wins": 799,
          "winRate": 100
        },
        {
          "heroHand": "Full House",
          "oppHand": "Full House",
          "threatPct": 37.88,
          "count": 2205,
          "wins": 1125,
          "winRate": 51
        },
        {
          "heroHand": "Full House",
          "oppHand": "Four of a Kind",
          "threatPct": 5.19,
          "count": 331,
          "wins": 0,
          "winRate": 0
        },
        {
          "heroHand": "Full House",
          "oppHand": "Straight Flush",
          "threatPct": 0.2,
          "count": 13,
          "wins": 0,
          "winRate": 0
        }
      ],
      [
        {
          "heroHand": "Four of a Kind",
          "oppHand": "High Card",
          "threatPct": 0,
          "count": 0,
          "wins": 0,
          "winRate": 0
        },
        {
          "heroHand": "Four of a Kind",
          "oppHand": "One Pair",
          "threatPct": 32.23,
          "count": 0,
          "wins": 0,
          "winRate": 0
        },
        {
          "heroHand": "Four of a Kind",
          "oppHand": "Two Pair",
          "threatPct": 55.37,
          "count": 113,
          "wins": 113,
          "winRate": 100
        },
        {
          "heroHand": "Four of a Kind",
          "oppHand": "Three of a Kind",
          "threatPct": 45.25,
          "count": 43,
          "wins": 43,
          "winRate": 100
        },
        {
          "heroHand": "Four of a Kind",
          "oppHand": "Straight",
          "threatPct": 15.29,
          "count": 49,
          "wins": 49,
          "winRate": 100
        },
        {
          "heroHand": "Four of a Kind",
          "oppHand": "Flush",
          "threatPct": 15.08,
          "count": 48,
          "wins": 48,
          "winRate": 100
        },
        {
          "heroHand": "Four of a Kind",
          "oppHand": "Full House",
          "threatPct": 46.49,
          "count": 225,
          "wins": 225,
          "winRate": 100
        },
        {
          "heroHand": "Four of a Kind",
          "oppHand": "Four of a Kind",
          "threatPct": 0.41,
          "count": 2,
          "wins": 2,
          "winRate": 100
        },
        {
          "heroHand": "Four of a Kind",
          "oppHand": "Straight Flush",
          "threatPct": 0.83,
          "count": 4,
          "wins": 0,
          "winRate": 0
        }
      ],
      [
        {
          "heroHand": "Straight Flush",
          "oppHand": "High Card",
          "threatPct": 12.94,
          "count": 0,
          "wins": 0,
          "winRate": 0
        },
        {
          "heroHand": "Straight Flush",
          "oppHand": "One Pair",
          "threatPct": 49.41,
          "count": 0,
          "wins": 0,
          "winRate": 0
        },
        {
          "heroHand": "Straight Flush",
          "oppHand": "Two Pair",
          "threatPct": 71.76,
          "count": 8,
          "wins": 8,
          "winRate": 100
        },
        {
          "heroHand": "Straight Flush",
          "oppHand": "Three of a Kind",
          "threatPct": 34.12,
          "count": 6,
          "wins": 6,
          "winRate": 100
        },
        {
          "heroHand": "Straight Flush",
          "oppHand": "Straight",
          "threatPct": 50.59,
          "count": 23,
          "wins": 23,
          "winRate": 100
        },
        {
          "heroHand": "Straight Flush",
          "oppHand": "Flush",
          "threatPct": 37.65,
          "count": 23,
          "wins": 23,
          "winRate": 100
        },
        {
          "heroHand": "Straight Flush",
          "oppHand": "Full House",
          "threatPct": 25.88,
          "count": 21,
          "wins": 21,
          "winRate": 100
        },
        {
          "heroHand": "Straight Flush",
          "oppHand": "Four of a Kind",
          "threatPct": 1.18,
          "count": 1,
          "wins": 1,
          "winRate": 100
        },
        {
          "heroHand": "Straight Flush",
          "oppHand": "Straight Flush",
          "threatPct": 3.53,
          "count": 3,
          "wins": 1,
          "winRate": 33.3
        }
      ]
    ]
  }
}